[
	{
		"description": "Retro-Musik mit Floppy Laufwerken!",
		"images":      [],
		"name": 	   "Floppyorgel",
		"team":		   ["Jonas Otto", "Thomas Kekeisen", "Felix Bäder", "Paul Nykiel"]	
	},
	{
		"description": "Felix baut sein eigenes Ambilight mit dem Raspberry PI",
		"images":      [],
		"name": 	   "Ambilight",
		"team":		   ["Felix Bäder"]	
	},
	{
		"description": "Informationen zu aktuellen Projekten",
		"images":      [],
		"name": 	   "Infodisplay",
		"team":		   ["Jonas Otto", "Thomas Kekeisen", "Paul Nykiel"]			
	},
	{
		"description": "Michael erstellt eine Webseite zum gemeinsamen hören von YouTube Videos",
		"images":      [],
		"name": 	   "Hackathon Radiostation",
		"team":		   ["Michael Malura"]			
	},
	{
		"description": "Alex baut eine SatNOGS Bodenstation für die Toolbox (und sucht noch Mitstreiter).",
		"images":      [
			{
				"name": "SatNOGS",
				"url": "images/satnogs.jpg"
			}
		],
		"name": 	   "SatNOGS",
		"team":		   ["Alex"]			
	},
	{
		"description": "Christian baut ein STM32F042 Breakout Board mit Micro USB Connector und TSSOP20 Package",
		"images":      [
			{
				"name": "Floyd",
				"url": "images/floyd-url.jpg"
			}
		],
		"name": 	   "Floyd",
		"team":		   ["Chistian"]			
	}
]